numtostring
